toastypy/__init__.py
toastypy/toastypy.py
toastypy/constructs/__init__.py
toastypy/constructs/lambda_warmer.py
toastypy-0.0.3.dist-info/LICENSE
toastypy-0.0.3.dist-info/METADATA
toastypy-0.0.3.dist-info/WHEEL
toastypy-0.0.3.dist-info/top_level.txt
toastypy-0.0.3.dist-info/RECORD
