Metadata-Version: 2.1
Name: toastypy
Version: 0.0.3
Summary: Simple python package for keeping your lambda functions warm using an eventbridge schedule
Author-email: Aidan Fogarty <aidan1fog@gmail.com>
Project-URL: Homepage, https://github.com/AidanFogarty/toasty
Project-URL: Issues, https://github.com/AidanFogarty/toasty/issues
Classifier: Programming Language :: Python :: 3
Classifier: License :: OSI Approved :: MIT License
Classifier: Operating System :: OS Independent
Requires-Python: >=3.8
License-File: LICENSE
